mkdocs_vwidalias
