Metadata-Version: 2.1
Name: mkdocs-vwidalias
Version: 0.1.5
Summary: MkDocs plugin to create /<ID>/ redirects from front-matter IDs
Home-page: https://github.com/yourname/mkdocs-vwidalias
Author: Gobidesert
Author-email: gobidesert.mf@gmail.com
License: MIT
Platform: UNKNOWN
Classifier: Development Status :: 3 - Alpha
Classifier: Intended Audience :: Developers
Classifier: License :: OSI Approved :: MIT License
Classifier: Programming Language :: Python
Classifier: Programming Language :: Python :: 3
Classifier: Programming Language :: Python :: 3 :: Only
Classifier: Programming Language :: Python :: 3.8
Classifier: Programming Language :: Python :: 3.9
Classifier: Programming Language :: Python :: 3.10
Classifier: Programming Language :: Python :: 3.11
Classifier: Programming Language :: Python :: 3.12
Classifier: Framework :: MkDocs
Classifier: Topic :: Documentation
Classifier: Operating System :: OS Independent
Requires-Python: >=3.8
